CHANGES.txt
COPYRIGHT.txt
CREDITS.txt
LICENSE.txt
MANIFEST.in
README.txt
TODO.txt
bootstrap.py
buildout.cfg
setup.cfg
setup.py
doc/Makefile
doc/api.rst
doc/changes.rst
doc/community.rst
doc/conf.py
doc/copyright.rst
doc/development.rst
doc/grok_samples.rst
doc/index.rst
doc/intro.rst
doc/license.rst
doc/make.bat
doc/samples.rst
src/zope/__init__.py
src/zope.pytest.egg-info/PKG-INFO
src/zope.pytest.egg-info/SOURCES.txt
src/zope.pytest.egg-info/dependency_links.txt
src/zope.pytest.egg-info/namespace_packages.txt
src/zope.pytest.egg-info/not-zip-safe
src/zope.pytest.egg-info/requires.txt
src/zope.pytest.egg-info/top_level.txt
src/zope/pytest/__init__.py
src/zope/pytest/__init__.pyc
src/zope/pytest/setup.py
src/zope/pytest/setup.pyc
src/zope/pytest/tests/__init__.py
src/zope/pytest/tests/__init__.pyc
src/zope/pytest/tests/ftesting.zcml
src/zope/pytest/tests/minimal.zcml
src/zope/pytest/tests/test_setup.py
src/zope/pytest/tests/test_setup.pyc
src/zope/pytest/tests/sample_fixtures/browser/mypkg3/__init__.py
src/zope/pytest/tests/sample_fixtures/browser/mypkg3/__init__.pyc
src/zope/pytest/tests/sample_fixtures/browser/mypkg3/app.py
src/zope/pytest/tests/sample_fixtures/browser/mypkg3/app.pyc
src/zope/pytest/tests/sample_fixtures/browser/mypkg3/browser.py
src/zope/pytest/tests/sample_fixtures/browser/mypkg3/browser.pyc
src/zope/pytest/tests/sample_fixtures/browser/mypkg3/configure.zcml
src/zope/pytest/tests/sample_fixtures/browser/mypkg3/ftesting.zcml
src/zope/pytest/tests/sample_fixtures/browser/mypkg3/interfaces.py
src/zope/pytest/tests/sample_fixtures/browser/mypkg3/interfaces.pyc
src/zope/pytest/tests/sample_fixtures/browser/mypkg3/tests/__init__.py
src/zope/pytest/tests/sample_fixtures/browser/mypkg3/tests/__init__.pyc
src/zope/pytest/tests/sample_fixtures/browser/mypkg3/tests/test_app.py
src/zope/pytest/tests/sample_fixtures/browser/mypkg3/tests/test_app.pyc
src/zope/pytest/tests/sample_fixtures/browser/mypkg3/tests/test_browser.py
src/zope/pytest/tests/sample_fixtures/browser/mypkg3/tests/test_browser.pyc
src/zope/pytest/tests/sample_fixtures/browser/mypkg3/tests/test_foo.py
src/zope/pytest/tests/sample_fixtures/browser/mypkg3/tests/test_foo.pyc
src/zope/pytest/tests/sample_fixtures/simple/mypkg/__init__.py
