Metadata-Version: 1.0
Name: zope.pytest
Version: 0.1
Summary: zope pytest integration
Home-page: http://pypi.python.org/pypi/zope.pytest
Author: Martijn Faassen and contributors
Author-email: zope-dev at zope dot org
License: ZPL
Platform: UNKNOWN
Classifier: Topic :: Software Development :: Libraries :: Python Modules
Classifier: Environment :: Web Environment
Classifier: Intended Audience :: Developers
Classifier: License :: OSI Approved :: Zope Public License
Classifier: Programming Language :: Python
Classifier: Framework :: Zope3
